veda_cli/__init__.py
veda_cli/applications/__init__.py
veda_cli/applications/ecco/__init__.py
veda_cli/applications/ecco/ecco_app.py
veda_cli/applications/wrf/__init__.py
veda_cli/datasets/__init__.py
veda_cli/executions/__init__.py
veda_cli/executions/ouput.py
veda_cli/main.py
veda_cli-0.0.16.dist-info/METADATA
veda_cli-0.0.16.dist-info/WHEEL
veda_cli-0.0.16.dist-info/entry_points.txt
veda_cli-0.0.16.dist-info/RECORD
