Metadata-Version: 2.1
Name: veda-cli
Version: 0.0.16
Summary: Command Line Client NASA VEDA Analytics
Author: Dimuthu Wannipurage
Author-email: dwannipu@iu.edu
Requires-Python: >=3.10,<4.0
Classifier: Programming Language :: Python :: 3
Classifier: Programming Language :: Python :: 3.10
Classifier: Programming Language :: Python :: 3.11
Requires-Dist: airavata-mft-cli (==0.1.10)
Requires-Dist: airavata_mft_sdk (==0.0.1-alpha27)
Requires-Dist: boto3 (>=1.26.0,<2.0.0)
Requires-Dist: grpcio (==1.46.3) ; platform_machine != "arm64"
Requires-Dist: grpcio (==1.47.0rc1) ; platform_machine == "arm64"
Requires-Dist: grpcio-tools (==1.46.3) ; platform_machine != "arm64"
Requires-Dist: grpcio-tools (==1.47.0rc1) ; platform_machine == "arm64"
Requires-Dist: paramiko (>=3.0.0,<4.0.0)
Requires-Dist: pick (==2.2.0)
Requires-Dist: pysondb (>=1.6.6,<2.0.0)
Requires-Dist: typer[all] (>=0.7.0,<0.8.0)
